yami/__init__.py
yami/__main__.py
yami/exceptions.py
yami/skill_loader.py
yami/version.py
yami/cli/__init__.py
yami/cli/alias.py
yami/cli/collection.py
yami/cli/compact.py
yami/cli/completion.py
yami/cli/config.py
yami/cli/data.py
yami/cli/database.py
yami/cli/flush.py
yami/cli/index.py
yami/cli/io.py
yami/cli/load.py
yami/cli/main.py
yami/cli/partition.py
yami/cli/query.py
yami/cli/role.py
yami/cli/segment.py
yami/cli/server.py
yami/cli/skill.py
yami/cli/user.py
yami/config/__init__.py
yami/config/loader.py
yami/config/profiles.py
yami/config/settings.py
yami/core/__init__.py
yami/core/client.py
yami/core/context.py
yami/core/job_cache.py
yami/core/schema.py
yami/output/__init__.py
yami/output/formatter.py
yami/skills/REFERENCE.md
yami/skills/SKILL.md
yami_cli-0.1.3.dist-info/METADATA
yami_cli-0.1.3.dist-info/WHEEL
yami_cli-0.1.3.dist-info/entry_points.txt
yami_cli-0.1.3.dist-info/RECORD
