Metadata-Version: 2.4
Name: yami-cli
Version: 0.1.3
Summary: Yet Another Milvus Interface - A command-line tool for Milvus vector database
Project-URL: Homepage, https://github.com/mmga-lab/yami-cli
Project-URL: Repository, https://github.com/mmga-lab/yami-cli
Author: Jeremy Zhu
License-Expression: Apache-2.0
Keywords: cli,command-line,milvus,vector-database
Classifier: Development Status :: 4 - Beta
Classifier: Environment :: Console
Classifier: Intended Audience :: Developers
Classifier: License :: OSI Approved :: Apache Software License
Classifier: Operating System :: OS Independent
Classifier: Programming Language :: Python :: 3
Classifier: Programming Language :: Python :: 3.10
Classifier: Programming Language :: Python :: 3.11
Classifier: Programming Language :: Python :: 3.12
Classifier: Topic :: Database
Classifier: Topic :: Utilities
Requires-Python: >=3.10
Requires-Dist: duckdb>=1.4.3
Requires-Dist: pyarrow>=22.0.0
Requires-Dist: pymilvus>=2.5.0
Requires-Dist: pyyaml>=6.0
Requires-Dist: rich>=13.0.0
Requires-Dist: tomli-w>=1.0.0
Requires-Dist: tomli>=2.0.0; python_version < '3.11'
Requires-Dist: typer[all]>=0.12.0
Provides-Extra: dev
Requires-Dist: mypy>=1.0; extra == 'dev'
Requires-Dist: pytest-cov>=4.0; extra == 'dev'
Requires-Dist: pytest>=7.0; extra == 'dev'
Requires-Dist: ruff>=0.1.0; extra == 'dev'
